{"id":"07","date":"23/01/2026","index":"ro-2026-01-04-07","title":"Studiu Suplimentar","bible":[{"name":"RMNN","verses":{"2Sam3-2Sam9":"<h2>2 Samuel 3:1-39</h2> <sup>1</sup> Războiul a ţinut mult între casa lui Saul şi casa lui David. David era tot mai tare, şi casa lui Saul mergea slăbind. <sup>2</sup> Lui David i s-au născut fii la Hebron. Întâiul lui născut a fost Amnon, din Ahinoam din Izreel; <sup>3</sup> al doilea, Chileab, din Abigail din Carmel, nevasta lui Nabal; al treilea, Absalom, fiul Maachei, fata lui Talmai, împăratul Gheşurului; <sup>4</sup> al patrulea, Adonia, fiul Haghitei; al cincilea, Şefatia, fiul Abitalei, <sup>5</sup> şi al şaselea, Itream, din Egla, nevasta lui David. Aceştia i s-au născut lui David la Hebron. <sup>6</sup> În timpul războiului dintre casa lui Saul şi casa lui David, Abner a ţinut cu tărie la casa lui Saul. <sup>7</sup> Dar Saul avusese o ţiitoare, numită Riţpa, fata lui Aiia. Şi Iş-Boşet a zis lui Abner: „Pentru ce ai intrat la ţiitoarea tatălui meu?” <sup>8</sup> Abner s-a mâniat foarte rău de cuvintele lui Iş-Boşet şi a răspuns: „Oare cap de câine sunt eu şi ţin cu Iuda? Eu dau astăzi dovadă de bunăvoinţă faţă de casa tatălui tău Saul, faţă de fraţii şi prietenii lui, nu te-am dat în mâinile lui David, şi astăzi îmi bagi vină pentru un păcat făcut cu femeia aceasta? <sup>9</sup> Dumnezeu să pedepsească cu toată asprimea pe Abner, dacă nu voi face cum a jurat Domnul lui David, <sup>10</sup> când i-a spus că împărăţia va fi luată de la casa lui Saul şi că scaunul de domnie al lui David va fi ridicat peste Israel şi peste Iuda, de la Dan până la Beer-Şeba”. <sup>11</sup> Iş-Boşet n-a îndrăznit să mai răspundă o vorbă lui Abner, pentru că se temea de el. <sup>12</sup> Abner a trimis soli la David să-i spună din partea lui: „A cui este ţara? Fă legământ cu mine, şi mâna mea te va ajuta să întorci la tine pe tot Israelul”. <sup>13</sup> El a răspuns: „Bine, voi face legământ cu tine, dar îţi cer un lucru: să nu-mi vezi faţa decât dacă-mi vei aduce mai întâi pe Mical, fata lui Saul, când vei veni la mine”. <sup>14</sup> Şi David a trimis soli lui Iş-Boşet, fiul lui Saul, să-i spună: „Dă-mi pe nevastă-mea Mical, cu care m-am logodit pentru o sută de prepuţuri de la filisteni”. <sup>15</sup> Iş-Boşet a trimis s-o ia de la bărbatul ei, Paltiel, fiul lui Laiş. <sup>16</sup> Şi bărbatul ei a mers după ea plângând până la Bahurim. Atunci, Abner i-a zis: „Pleacă şi întoarce-te!” Şi el s-a întors. <sup>17</sup> Abner a stat de vorbă cu bătrânii lui Israel şi le-a zis: „Odinioară voi doreaţi să aveţi împărat pe David; <sup>18</sup> puneţi-l acum, căci Domnul a zis despre el: ‘Prin robul Meu David voi izbăvi pe poporul Meu Israel din mâna filistenilor şi din mâna tuturor vrăjmaşilor lui’.” <sup>19</sup> Abner a vorbit şi lui Beniamin şi s-a dus să spună în auzul lui David la Hebron ce hotărâse Israel şi toată casa lui Beniamin. <sup>20</sup> A ajuns la David în Hebron, însoţit de douăzeci de oameni, şi David a dat un ospăţ în cinstea lui Abner şi a celor care erau cu el. <sup>21</sup> Abner a zis lui David: „Mă voi scula şi voi pleca să strâng tot Israelul la domnul meu, împăratul, ca să facă legământ cu tine şi să domneşti în totul după dorinţa ta”. David a dat drumul lui Abner, care a plecat în pace. <sup>22</sup> Ioab şi oamenii lui David s-au întors de la urmărirea unei cete şi au adus cu ei o mare pradă. Abner nu mai era la David, în Hebron, căci David îi dăduse drumul şi plecase în pace. <sup>23</sup> Când a venit Ioab cu toată ceata lui, i s-a spus: „Abner, fiul lui Ner, a venit la împărat, care i-a dat drumul şi s-a dus în pace”. <sup>24</sup> Ioab s-a dus la împărat şi a zis: „Ce ai făcut? Abner a venit la tine. Pentru ce i-ai dat drumul şi l-ai lăsat să plece? <sup>25</sup> Tu cunoşti pe Abner, fiul lui Ner! A venit să te înşele, ca să-ţi pândească paşii şi să ştie tot ce faci.” <sup>26</sup> Şi Ioab, după ce a plecat de la David, a trimis pe urmele lui Abner nişte soli care l-au adus înapoi de la fântâna fără apă Sira: David nu ştia nimic. <sup>27</sup> Când s-a întors Abner la Hebron, Ioab l-a tras deoparte în mijlocul porţii ca să-i vorbească în taină şi l-a lovit acolo în pântece şi l-a omorât, ca să răzbune moartea fratelui său Asael. <sup>28</sup> David a aflat apoi şi a zis: „Nevinovat sunt eu şi împărăţia mea pe vecie înaintea Domnului de sângele lui Abner, fiul lui Ner. <sup>29</sup> Sângele acesta să cadă asupra lui Ioab şi asupra întregii case a tatălui său! Totdeauna să fie în casa lui Ioab cineva atins de o scurgere de sămânţă sau de lepră, sau care să se rezeme în cârjă, sau să cadă ucis de sabie, sau să ducă lipsă de pâine!” <sup>30</sup> Astfel, Ioab şi fratele său Abişai au omorât pe Abner pentru că omorâse pe fratele lor Asael în lupta de la Gabaon. <sup>31</sup> David a zis lui Ioab şi întregului popor care era cu el: „Rupeţi-vă hainele, încingeţi-vă cu saci şi bociţi-vă înaintea lui Abner!” Şi împăratul David mergea în urma sicriului. <sup>32</sup> Au îngropat pe Abner la Hebron. Împăratul a ridicat glasul şi a plâns la mormântul lui Abner, şi tot poporul plângea. <sup>33</sup> Împăratul a făcut următoarea cântare de jale pentru Abner şi a zis:„Să moară Abner cum moare un mişel? <sup>34</sup> N-aveai nici mâinile legate,Nici picioarele puse în lanţuriAi căzut cum cade cineva înaintea celor răi!”Şi tot poporul a plâns şi mai mult după Abner. <sup>35</sup> Tot poporul s-a apropiat de David ca să-l facă să mănânce ceva cât era încă ziuă, dar David a jurat zicând: „Să mă pedepsească Dumnezeu cu toată asprimea dacă voi gusta pâine sau altceva înainte de apusul soarelui!” <sup>36</sup> Lucrul acesta a fost cunoscut şi plăcut la tot poporul; toţi au găsit că era bine ce făcuse împăratul. <sup>37</sup> Tot poporul şi tot Israelul au înţeles în ziua aceea că Abner, fiul lui Ner, nu fusese ucis din porunca împăratului. <sup>38</sup> Împăratul a zis slujitorilor săi: „Nu ştiţi că o căpetenie, un om mare, a căzut astăzi în Israel? <sup>39</sup> Eu sunt încă slab, măcar că am primit ungerea împărătească, şi oamenii aceştia, fiii Ţeruiei, sunt prea puternici pentru mine. Domnul să răsplătească după răutatea celui ce a făcut răul!”\n\n<h2>2 Samuel 4:1-12</h2> <sup>1</sup> Când a auzit fiul lui Saul că Abner a murit la Hebron, mâinile i-au rămas fără putere şi tot Israelul s-a înspăimântat. <sup>2</sup> Fiul lui Saul avea doi capi peste cetele de război, dintre care unul se numea Baana, iar altul, Recab; erau fiii lui Rimon din Beerot, dintre fiii lui Beniamin. Căci Beerot era privit ca făcând parte din Beniamin, <sup>3</sup> şi beerotiţii fugiseră la Ghitaim, unde au locuit până în ziua de azi. <sup>4</sup> Ionatan, fiul lui Saul, avea un fiu olog de picioare şi în vârstă de cinci ani când a venit din Izreel vestea morţii lui Saul şi a lui Ionatan; doica lui l-a luat şi a fugit şi, fiindcă se grăbea să fugă, a căzut şi a rămas olog; numele lui era Mefiboşet. <sup>5</sup> Şi fiii lui Rimon din Beerot, Recab şi Baana, s-au dus în timpul zădufului zilei în casa lui Iş-Boşet, care îşi făcea somnul de amiază. <sup>6</sup> Au pătruns până în mijlocul casei, dându-se drept negustori de grâu, şi l-au lovit în pântece; apoi Recab şi Baana, fratele său, au scăpat. <sup>7</sup> Au intrat în casă pe când el era culcat pe pat, în odaia lui de dormit, l-au lovit, l-au omorât şi i-au tăiat capul. I-au luat capul şi au mers toată noaptea prin câmpie. <sup>8</sup> Au adus capul lui Iş-Boşet la David, în Hebron, şi au zis împăratului: „Iată capul lui Iş-Boşet, fiul lui Saul, vrăjmaşul tău, care voia să-ţi ia viaţa; Domnul răzbună azi pe împărat, domnul meu, împotriva lui Saul şi împotriva neamului lui.” <sup>9</sup> David a răspuns lui Recab şi lui Baana, fratele său, fiii lui Rimon din Beerot: „Viu este Domnul, care m-a izbăvit din orice primejdie, <sup>10</sup> că pe cel ce a venit să-mi spună: ‘Iată, Saul a murit’ şi care credea că-mi aduce o veste bună, l-am prins şi l-am omorât la Ţiclag, ca să-l răsplătesc pentru ştirea lui, <sup>11</sup> şi, când nişte răi au ucis pe un om nevinovat în casa lui şi în patul lui, cu cât mai mult îi voi cere sângele din mâinile voastre şi vă voi nimici de pe pământ.” <sup>12</sup> Şi David a poruncit oamenilor lui să-i omoare; le-au tăiat mâinile şi picioarele şi i-au spânzurat la marginea iazului din Hebron. Au luat apoi capul lui Iş-Boşet şi l-au îngropat în mormântul lui Abner, la Hebron.\n\n<h2>2 Samuel 5:1-25</h2> <sup>1</sup> Toate seminţiile lui Israel au venit la David, în Hebron, şi au zis: „Iată că noi suntem os din oasele tale şi carne din carnea ta. <sup>2</sup> Chiar odinioară, când Saul era împăratul nostru, tu povăţuiai şi strângeai pe Israel. Domnul ţi-a zis: ‘Tu vei paşte pe poporul Meu Israel şi vei fi căpetenia lui Israel’.” <sup>3</sup> Astfel, toţi bătrânii lui Israel au venit la împărat, în Hebron, şi împăratul David a făcut legământ cu ei la Hebron, înaintea Domnului. Şi au uns pe David împărat peste Israel. <sup>4</sup> David era în vârstă de treizeci de ani când s-a făcut împărat şi a domnit patruzeci de ani. <sup>5</sup> La Hebron, a domnit peste Iuda şapte ani şi şase luni şi, la Ierusalim, a domnit treizeci şi trei de ani peste tot Israelul şi Iuda. <sup>6</sup> Împăratul a mers cu oamenii lui asupra Ierusalimului împotriva iebusiţilor, locuitorii ţării. Ei au zis lui David: „Să nu intri aici, căci şi orbii, şi ologii ţi se vor împotrivi!” Prin aceasta voiau să spună că David nu va intra cu niciun chip aici. <sup>7</sup> Dar David a pus mâna pe cetăţuia Sionului: aceasta este cetatea lui David. <sup>8</sup> David zisese în ziua aceea: „Oricine va bate pe iebusiţi să arunce în canal pe şchiopii şi pe orbii aceia care sunt vrăjmaşii lui David”. De aceea se zice: „Orbul şi şchiopul să nu intre în Casa Domnului.” <sup>9</sup> David s-a aşezat în cetăţuie, pe care a numit-o cetatea lui David. A făcut întărituri de jur împrejur, în afară şi înăuntrul lui Milo <i class=\"trans-change\">(Cetăţuie)</i>. <sup>10</sup> David ajungea tot mai mare şi Domnul, Dumnezeul oştirilor, era cu el. <sup>11</sup> Hiram, împăratul Tirului, a trimis soli lui David şi lemn de cedru, şi tâmplari, şi cioplitori de piatră, care au zidit o casă lui David. <sup>12</sup> David a cunoscut că Domnul îl întărea ca împărat al lui Israel şi că-i ridica împărăţia din pricina poporului Său, Israel. <sup>13</sup> David şi-a mai luat ţiitoare şi neveste din Ierusalim după ce a venit din Hebron şi i s-au născut iarăşi fii şi fiice. <sup>14</sup> Iată numele celor ce i s-au născut la Ierusalim: Şamua, Şobab, Natan, Solomon, <sup>15</sup> Ibhar, Elişua, Nefeg, Iafia, <sup>16</sup> Elişama, Eliada şi Elifelet. <sup>17</sup> Filistenii au aflat că David fusese uns împărat peste Israel şi s-au suit toţi să-l caute. David, căruia i s-a dat de ştire, s-a pogorât în cetăţuie. <sup>18</sup> Filistenii au venit şi s-au răspândit în valea Refaim. <sup>19</sup> David a întrebat pe Domnul: „Să mă sui împotriva filistenilor? Îi vei da în mâinile mele?” Şi Domnul a zis lui David: „Suie-te, căci voi da pe filisteni în mâinile tale.” <sup>20</sup> David a venit la Baal-Peraţim, unde i-a bătut. Apoi a zis: „Domnul a risipit pe vrăjmaşii mei dinaintea mea, ca nişte ape care se rup.” De aceea s-a dat locului aceluia numele Baal-Peraţim <i class=\"trans-change\">(Şesul rupturii)</i>. <sup>21</sup> Ei şi-au lăsat idolii acolo şi David şi oamenii lui i-au luat. <sup>22</sup> Filistenii s-au suit din nou şi s-au răspândit în valea Refaim. <sup>23</sup> David a întrebat pe Domnul. Şi Domnul a zis: „Să nu te sui, ci ia-i pe la spate şi mergi asupra lor în dreptul duzilor. <sup>24</sup> Când vei auzi un vuiet de paşi în vârfurile duzilor, atunci să te grăbeşti, căci Domnul merge înaintea ta, ca să bată oştirea filistenilor.” <sup>25</sup> David a făcut cum îi poruncise Domnul şi a bătut pe filisteni de la Gheba până la Ghezer.\n\n<h2>2 Samuel 6:1-23</h2> <sup>1</sup> David a strâns iarăşi pe toţi aleşii lui Israel în număr de treizeci de mii de oameni. <sup>2</sup> Şi David, cu tot poporul care era cu el, a pornit de la Baale-Iuda ca să suie de acolo chivotul lui Dumnezeu, înaintea căruia este chemat Numele Domnului oştirilor, care stă între heruvimi, deasupra chivotului. <sup>3</sup> Au pus chivotul lui Dumnezeu într-un car nou şi l-au ridicat din casa lui Abinadab, de pe deal; Uza şi Ahio, fiul lui Abinadab, cârmuiau carul cel nou. <sup>4</sup> L-au luat dar din casa lui Abinadab, de pe deal; Uza mergea alături de chivotul lui Dumnezeu şi Ahio mergea înaintea chivotului. <sup>5</sup> David şi toată casa lui Israel cântau înaintea Domnului cu tot felul de instrumente de lemn de chiparos, cu harpe, cu lăute, cu timpane, cu fluiere şi cu ţimbale. <sup>6</sup> Când au ajuns la aria lui Nacon, Uza a întins mâna spre chivotul lui Dumnezeu şi l-a apucat, pentru că erau să-l răstoarne boii. <sup>7</sup> Domnul S-a aprins de mânie împotriva lui Uza şi Dumnezeu l-a lovit pe loc pentru păcatul lui şi a murit acolo, lângă chivotul lui Dumnezeu. <sup>8</sup> David s-a întristat că Dumnezeu lovise pe Uza cu o astfel de pedeapsă, rupându-l pe loc. Şi locul acesta a fost numit până în ziua de azi Pereţ-Uza <i class=\"trans-change\">(Ruperea lui Uza)</i>. <sup>9</sup> David s-a temut de Domnul în ziua aceea şi a zis: „Cum să intre chivotul Domnului la mine?” <sup>10</sup> N-a vrut să aducă chivotul Domnului la el, în cetatea lui David, şi l-a dus în casa lui Obed-Edom din Gat. <sup>11</sup> Chivotul Domnului a rămas trei luni în casa lui Obed-Edom din Gat şi Domnul a binecuvântat pe Obed-Edom şi toată casa lui. <sup>12</sup> Au venit şi au spus împăratului David: „Domnul a binecuvântat casa lui Obed-Edom şi tot ce avea din pricina chivotului lui Dumnezeu.” Atunci, David a pornit şi a suit chivotul lui Dumnezeu din casa lui Obed-Edom în cetatea lui David, în mijlocul veseliei. <sup>13</sup> Când cei ce duceau chivotul Domnului au făcut şase paşi, au jertfit un bou şi un viţel gras. <sup>14</sup> David juca din răsputeri înaintea Domnului şi era încins cu efodul de in subţire. <sup>15</sup> Astfel au suit David şi toată casa lui Israel chivotul Domnului în strigăte de bucurie şi în sunet de trâmbiţe. <sup>16</sup> Pe când chivotul Domnului intra în cetatea lui David, Mical, fata lui Saul, se uita pe fereastră şi, văzând pe împăratul David sărind şi jucând înaintea Domnului, l-a dispreţuit în inima ei. <sup>17</sup> După ce au adus chivotul Domnului, l-au pus la locul lui, în mijlocul cortului pe care-l ridicase David pentru chivot, şi David a adus înaintea Domnului arderi-de-tot şi jertfe de mulţumire. <sup>18</sup> Când a isprăvit David de adus arderile-de-tot şi jertfele de mulţumire, a binecuvântat poporul în Numele Domnului oştirilor. <sup>19</sup> Apoi a împărţit la tot poporul, la toată mulţimea lui Israel, bărbaţi şi femei, fiecăruia câte o pâine, o bucată de carne şi o turtă de stafide. Şi tot poporul a plecat, fiecare la casa lui. <sup>20</sup> David s-a întors să-şi binecuvânteze casa. Mical, fata lui Saul, i-a ieşit înainte şi a zis: „Cu câtă cinste s-a purtat azi împăratul lui Israel descoperindu-se înaintea slujnicelor supuşilor lui, cum s-ar descoperi un om de nimic!” <sup>21</sup> David a răspuns Micalei: „Înaintea Domnului, care m-a ales mai presus de tatăl tău şi de toată casa lui, ca să mă pună căpetenie peste poporul Domnului, peste Israel, înaintea Domnului am jucat. <sup>22</sup> Vreau să mă arăt şi mai de nimic decât de data asta şi să mă înjosesc în ochii mei, totuşi voi fi în cinste la slujnicele de care vorbeşti.” <sup>23</sup> Şi Mical, fata lui Saul, n-a avut copii până în ziua morţii ei.\n\n<h2>2 Samuel 7:1-29</h2> <sup>1</sup> Când a locuit împăratul în casa lui şi când i-a dat odihnă Domnul, după ce l-a izbăvit de toţi vrăjmaşii care-l înconjurau, <sup>2</sup> a zis prorocului Natan: „Iată! Eu locuiesc într-o casă de cedru, şi chivotul lui Dumnezeu locuieşte într-un cort.” <sup>3</sup> Natan a răspuns împăratului: „Du-te şi fă tot ce ai în inimă, căci Domnul este cu tine.” <sup>4</sup> În noaptea următoare, Cuvântul Domnului a vorbit lui Natan: <sup>5</sup> „Du-te şi spune robului meu David: ‘Aşa vorbeşte Domnul: «Oare tu Îmi vei zidi o casă ca să locuiesc în ea? <sup>6</sup> Dar Eu n-am locuit într-o casă din ziua când am scos pe copiii lui Israel din Egipt până în ziua aceasta, ci am călătorit într-un cort drept locuinţă. <sup>7</sup> Pretutindeni pe unde am mers cu toţi copiii lui Israel, am spus Eu oare vreo vorbă vreuneia din seminţiile lui Israel, căreia îi poruncisem să pască pe poporul Meu, Israel, zicând: Pentru ce nu-Mi zidiţi o casă de cedru?»’ <sup>8</sup> Acum să spui robului Meu David: ‘Aşa vorbeşte Domnul oştirilor: «Te-am luat de la păşune, de la oi, ca să fii căpetenie peste poporul Meu, peste Israel; <sup>9</sup> am fost cu tine pretutindeni pe unde ai mers, am nimicit pe toţi vrăjmaşii tăi dinaintea ta şi ţi-am făcut numele mare, ca numele celor mari de pe pământ; <sup>10</sup> am dat un loc poporului Meu, lui Israel, şi l-am sădit ca să locuiască în el şi să nu mai fie tulburat, ca să nu-l mai apese cei răi ca mai înainte <sup>11</sup> şi ca pe vremea când pusesem judecători peste poporul Meu, Israel. Ţi-am dat odihnă izbăvindu-te de toţi vrăjmaşii tăi. Şi Domnul îţi vesteşte că-ţi va zidi o casă. <sup>12</sup> Când ţi se vor împlini zilele şi vei fi culcat cu părinţii tăi, Eu îţi voi ridica un urmaş după tine, care va ieşi din trupul tău, şi-i voi întări împărăţia. <sup>13</sup> El va zidi Numelui Meu o casă şi voi întări pe vecie scaunul de domnie al împărăţiei lui. <sup>14</sup> Eu îi voi fi Tată şi el Îmi va fi fiu. Dacă va face răul, îl voi pedepsi cu o nuia omenească şi cu lovituri omeneşti; <sup>15</sup> dar harul Meu nu se va depărta de la el, cum l-am depărtat de la Saul, pe care l-am îndepărtat dinaintea ta. <sup>16</sup> Ci casa ta şi împărăţia ta vor dăinui veşnic înaintea Mea şi scaunul tău de domnie va fi întărit pe vecie».’ ” <sup>17</sup> Natan a spus lui David toate aceste cuvinte şi toată vedenia aceasta. <sup>18</sup> Şi împăratul David s-a dus şi s-a înfăţişat înaintea Domnului şi a zis: „Cine sunt eu, Doamne, Dumnezeule, şi ce este casa mea, de m-ai făcut să ajung unde sunt? <sup>19</sup> Şi încă atât este puţin înaintea Ta, Doamne, Dumnezeule! Tu vorbeşti despre casa robului Tău şi în viitor. Şi binevoieşti să înveţi pe un om cu privire la aceste lucruri, Doamne, Dumnezeule! <sup>20</sup> Ce Ţi-ar putea spune David mai mult? Tu cunoşti pe robul Tău, Doamne, Dumnezeule! <sup>21</sup> După cuvântul Tău şi după inima Ta, Tu ai făcut toate aceste lucruri mari, ca să le descoperi robului Tău! <sup>22</sup> Ce mare eşti Tu, Doamne, Dumnezeule! Căci nimeni nu este ca Tine şi nu este alt Dumnezeu afară de Tine, după tot ce am auzit cu urechile noastre. <sup>23</sup> Este oare pe pământ un singur neam care să fie ca poporul Tău, ca Israel, pe care a venit să-l răscumpere Dumnezeu, ca să facă din el poporul Lui, ca să-Şi facă un Nume şi ca să facă pentru el, pentru ţara Ta, minuni şi semne, izgonind dinaintea poporului Tău, pe care l-ai răscumpărat din Egipt, neamuri şi pe dumnezeii lor? <sup>24</sup> Tu ai întărit pe poporul Tău, Israel, ca să fie poporul Tău pe vecie, şi Tu, Doamne, Te-ai făcut Dumnezeul lui. <sup>25</sup> Acum, Doamne, Dumnezeule, fă să rămână în veci cuvântul pe care l-ai rostit asupra robului Tău şi asupra casei lui şi lucrează după cuvântul Tău. <sup>26</sup> Slăvit să fie Numele Tău pe vecie şi să se zică: ‘Domnul oştirilor este Dumnezeul lui Israel. Şi casa robului Tău David să rămână înaintea Ta!’ <sup>27</sup> Căci Tu Însuţi, Doamne al oştirilor, Dumnezeul lui Israel, Te-ai descoperit robului Tău zicând: ‘Eu îţi voi întemeia o casă!’ De aceea a îndrăznit robul Tău să-Ţi facă această rugăciune. <sup>28</sup> Acum, Doamne, Dumnezeule, Tu eşti Dumnezeu şi cuvintele Tale sunt adevăr şi Tu ai vestit harul acesta robului Tău. <sup>29</sup> Binecuvântează dar casa robului Tău, ca să dăinuiască pe vecie înaintea Ta! Căci Tu, Doamne, Dumnezeule, ai vorbit şi, prin binecuvântarea Ta, casa robului Tău va fi binecuvântată pe vecie”.\n\n<h2>2 Samuel 8:1-18</h2> <sup>1</sup> După aceea, David a bătut pe filisteni şi i-a smerit şi a luat din mâna filistenilor cârmuirea capitalei lor. <sup>2</sup> A bătut pe moabiţi şi i-a măsurat cu o frânghie, punându-i să se culce la pământ; a măsurat două frânghii ca să-i omoare şi o frânghie plină ca să-i lase vii. Şi moabiţii au fost supuşi lui David şi i-au plătit un bir. <sup>3</sup> David a bătut pe Hadadezer, fiul lui Rehob, împăratul din Ţoba, când s-a dus să-şi aşeze iarăşi stăpânirea peste râul Eufrat. <sup>4</sup> David i-a luat o mie şapte sute de călăreţi şi douăzeci de mii de pedeştri; a tăiat vinele cailor de trăsură şi n-a păstrat cai decât pentru o sută de care. <sup>5</sup> Sirienii din Damasc au venit în ajutorul lui Hadadezer, împăratul din Ţoba, şi David a ucis douăzeci şi două de mii de sirieni. <sup>6</sup> David a pus strajă în Siria Damascului. Şi sirienii au fost supuşi lui David şi i-au plătit un bir. Domnul ocrotea pe David oriunde se ducea. <sup>7</sup> Şi David a luat scuturile de aur pe care le aveau slujitorii lui Hadadezer şi le-a adus la Ierusalim. <sup>8</sup> Împăratul David a mai luat multă aramă din Betah şi din Berotai, cetăţile lui Hadadezer. <sup>9</sup> Toi, împăratul Hamatului, a auzit că David bătuse toată oştirea lui Hadadezer <sup>10</sup> şi a trimis pe fiul său Ioram la împăratul David, ca să-i ureze de bine şi să-l laude că a pornit lupta împotriva lui Hadadezer şi că l-a bătut. Căci Toi era în război cu Hadadezer. Ioram a adus vase de argint, vase de aur şi vase de aramă. <sup>11</sup> Împăratul David le-a închinat Domnului, cum închinase şi argintul şi aurul luate de la toate neamurile pe care le biruise, <sup>12</sup> din Siria, din Moab, de la fiii lui Amon, de la filisteni, de la Amalec şi din prada de la Hadadezer, fiul lui Rehob, împăratul din Ţoba. <sup>13</sup> La întoarcerea de la biruinţa lui asupra sirienilor, David şi-a făcut iarăşi un nume bătând în Valea Sării optsprezece mii de edomiţi. <sup>14</sup> A pus străji în Edom, a pus străji în tot Edomul. Şi tot Edomul a fost supus lui David. Domnul ocrotea pe David pretutindeni pe unde mergea. <sup>15</sup> David a împărăţit peste Israel şi făcea judecată şi dreptate la tot poporul lui. <sup>16</sup> Ioab, fiul Ţeruiei, era mai-mare peste oştire; Iosafat, fiul lui Ahilud, era mai-mare peste scriitori; <sup>17</sup> Ţadoc, fiul lui Ahitub, şi Ahimelec, fiul lui Abiatar, erau preoţi; Seraia era logofăt; <sup>18</sup> Benaia, fiul lui Iehoiada, era căpetenia cheretiţilor şi a peletiţilor; şi fiii lui David erau mari dregători.\n\n<h2>2 Samuel 9:1-13</h2> <sup>1</sup> David a zis: „A mai rămas cineva din casa lui Saul, ca să-i fac bine din pricina lui Ionatan?” <sup>2</sup> Era un slujitor din casa lui Saul, numit Ţiba, pe care l-au adus la David. Împăratul i-a zis: „Tu eşti Ţiba?” Şi el a răspuns: „Robul tău, da!” <sup>3</sup> Împăratul a zis: „Nu mai este nimeni din casa lui Saul, ca să mă port cu el cu o bunătate ca bunătatea lui Dumnezeu?” Şi Ţiba a răspuns împăratului: „Mai este un fiu al lui Ionatan, olog de picioare”. <sup>4</sup> Împăratul a zis: „Unde este?” Şi Ţiba a răspuns împăratului: „Este în casa lui Machir, fiul lui Amiel, la Lodebar”. <sup>5</sup> Împăratul David l-a trimis să-l ia din casa lui Machir, fiul lui Amiel, din Lodebar. <sup>6</sup> Şi Mefiboşet, fiul lui Ionatan, fiul lui Saul, a venit la David, a căzut cu faţa la pământ şi s-a închinat. David a zis: „Mefiboşet!” Şi el a răspuns: „Iată robul tău!” <sup>7</sup> David i-a zis: „Nu te teme, căci vreau să-ţi fac bine din pricina tatălui tău Ionatan. Îţi voi da înapoi toate pământurile tatălui tău, Saul, şi vei mânca totdeauna la masa mea”. <sup>8</sup> El s-a închinat şi a zis: „Cine este robul tău, ca să te uiţi la un câine mort ca mine?” <sup>9</sup> Împăratul a chemat pe Ţiba, slujbaşul lui Saul, şi i-a zis: „Dau fiului stăpânului tău tot ce era al lui Saul şi tot ce avea toată casa lui. <sup>10</sup> Tu să lucrezi pământurile pentru el, tu, fiii tăi şi robii tăi, şi să strângi roadele, ca fiul stăpânului tău să aibă pâine de mâncare, şi Mefiboşet, fiul stăpânului tău, va mânca totdeauna la masa mea”. Şi Ţiba avea cincisprezece fii şi douăzeci de robi. <sup>11</sup> El a zis împăratului: „Robul tău va face tot ce porunceşte împăratul, domnul meu, robului său”. Şi Mefiboşet a mâncat la masa lui David, ca unul din fiii împăratului. <sup>12</sup> Mefiboşet avea un fiu mic, numit Mica, şi toţi cei ce locuiau în casa lui Ţiba erau robii lui Mefiboşet. <sup>13</sup> Mefiboşet locuia la Ierusalim, căci mânca totdeauna la masa împăratului. El era olog de amândouă picioarele."}}],"content":"<p>„Toată iubirea părintească ce a venit din generație în generație prin canalele inimii omenești, toate izvoarele de blândețe care s-au deschis în sufletul oamenilor nu sunt decât mici pâraie față de nemărginitul ocean atunci când sunt comparate cu iubirea infinită și inepuizabilă a lui Dumnezeu. […] Poți studia veacuri întregi această iubire, dar nu vei putea înțelege niciodată pe deplin înălțimea, lărgimea, adâncimea și lungimea iubirii lui Dumnezeu, care L-a dat pe Fiul Său să moară pentru lume. Nici chiar veșnicia nu va putea să o descopere pe deplin. Totuși, studiind Biblia și meditând asupra vieții Domnului Hristos și a planului de mântuire, vom înțelege tot mai mult” (Ellen G. White, Mărturii pentru biserică, vol. 5, p. 740).</p>\n<p>„Când suntem formați, la fel ca Moise, în școala lui Hristos, ce învățăm? […] Cu cât învățăm mai mult în această școală, cu atât vom progresa în blândețea și smerenia minții. Nu trebuie să considerăm că am învățat tot ce merită știut. Ar trebui să folosim în cel mai bun mod talentele pe care Dumnezeu ni le-a dat, astfel încât, atunci când vom fi schimbați din starea de muritori în cea de nemuritori, să nu lăsăm în urmă ceea ce am dobândit, ci să le luăm cu noi în lumea de dincolo. De-a lungul veacurilor nesfârșite ale eternității, Hristos și lucrarea Sa de răscumpărare vor fi tema studiului nostru” (Ellen G. White, Manuscrisul 36, 1885).</p>\n<p><strong>Zilnic:</strong> <a class=\"verse\" verse=\"2Sam3-2Sam9\">2 Samuel 3 – 9</a>; Ellen G. White, Dietă și hrană, cap. 2, „Necumpătarea, un păcat” – „Efectul asupra discernământului și puterii de decizie”</p>\n<p><code>1. Cât a ținut războiul între casa lui Saul și casa lui David?</code></p>\n<p><code>2. Cine și cu ce au zidit o casă lui David?</code></p>\n<p><code>3. Din a cui casă a fost luat chivotul și pus într-un car nou?</code></p>\n<p><code>4. Ce făcea David întregului popor?</code></p>\n<p><code>5. Ce au priceput numai câțiva care sunt îndeajuns de treji?</code></p>\n"}